docs/Makefile
docs/modules.rst
docs/pylops_mpi.rst
docs/source/adding.rst
docs/source/benchmarking.rst
docs/source/changelog.rst
docs/source/conf.py
docs/source/contributing.rst
docs/source/credits.rst
docs/source/gpu.rst
docs/source/index.rst
docs/source/installation.rst
docs/source/_static/favicon.ico
docs/source/_static/pylopsmpi.png
docs/source/_static/pylopsmpi_b.png
docs/source/_static/style.css
docs/source/_static/css/custom.css
docs/source/_templates/layout.html
docs/source/_templates/autosummary/base.rst
docs/source/_templates/autosummary/class.rst
docs/source/_templates/autosummary/exception.rst
docs/source/_templates/autosummary/function.rst
docs/source/_templates/autosummary/module.rst
docs/source/api/index.rst
examples/README.rst
examples/plot_cgls.py
examples/plot_derivative.py
examples/plot_distributed_array.py
examples/plot_matrixmult.py
examples/plot_mdc.py
examples/plot_mpilinop.py
examples/plot_stacked_array.py
examples/plot_stacking.py
pylops_mpi/DistributedArray.py
pylops_mpi/LinearOperator.py
pylops_mpi/StackedLinearOperator.py
pylops_mpi/__init__.py
pylops_mpi/version.py
pylops_mpi/basicoperators/BlockDiag.py
pylops_mpi/basicoperators/FirstDerivative.py
pylops_mpi/basicoperators/Gradient.py
pylops_mpi/basicoperators/HStack.py
pylops_mpi/basicoperators/Laplacian.py
pylops_mpi/basicoperators/MatrixMult.py
pylops_mpi/basicoperators/SecondDerivative.py
pylops_mpi/basicoperators/VStack.py
pylops_mpi/basicoperators/__init__.py
pylops_mpi/optimization/__init__.py
pylops_mpi/optimization/basic.py
pylops_mpi/optimization/cls_basic.py
pylops_mpi/plotting/__init__.py
pylops_mpi/plotting/plotting.py
pylops_mpi/signalprocessing/Fredholm1.py
pylops_mpi/signalprocessing/__init__.py
pylops_mpi/utils/__init__.py
pylops_mpi/utils/_nccl.py
pylops_mpi/utils/benchmark.py
pylops_mpi/utils/decorators.py
pylops_mpi/utils/deps.py
pylops_mpi/utils/dottest.py
pylops_mpi/waveeqprocessing/MDC.py
pylops_mpi/waveeqprocessing/__init__.py
pylops_mpi-0.3.0.dist-info/licenses/LICENSE
testdata/avo/poststack_model.npz
pylops_mpi-0.3.0.dist-info/METADATA
pylops_mpi-0.3.0.dist-info/WHEEL
pylops_mpi-0.3.0.dist-info/top_level.txt
pylops_mpi-0.3.0.dist-info/RECORD
