Metadata-Version: 2.4
Name: pylops-mpi
Version: 0.3.0
Summary: Python library implementing linear operators with MPI
Author-email: Rohan Babbar <rohanbabbar0408@gmail.com>, Matteo Ravasi <matteoravasi@gmail.com>
License:                    GNU LESSER GENERAL PUBLIC LICENSE
Keywords: algebra,inverse problems,large-scale optimization,distributed computing
Classifier: Development Status :: 3 - Alpha
Classifier: Intended Audience :: Developers
Classifier: Intended Audience :: Science/Research
Classifier: Intended Audience :: Education
Classifier: License :: OSI Approved :: GNU Lesser General Public License v3 (LGPLv3)
Classifier: Natural Language :: English
Classifier: Programming Language :: Python :: 3 :: Only
Classifier: Programming Language :: Python :: 3.8
Classifier: Programming Language :: Python :: 3.9
Classifier: Topic :: Scientific/Engineering :: Mathematics
License-File: LICENSE
Requires-Dist: numpy>=1.15.0
Requires-Dist: scipy>=1.4.0
Requires-Dist: pylops>=2.0
Requires-Dist: mpi4py
Requires-Dist: matplotlib
Dynamic: license-file
